{"v":"5.3.4","fr":25,"ip":0,"op":61,"w":800,"h":800,"nm":"{","ddd":0,"assets":[],"layers":[{"ddd":0,"ind":1,"ty":4,"nm":"circulo/mensajeria contornos","sr":1,"ks":{"o":{"a":0,"k":100,"ix":11},"r":{"a":0,"k":0,"ix":10},"p":{"a":0,"k":[400,400,0],"ix":2},"a":{"a":0,"k":[400,400,0],"ix":1},"s":{"a":1,"k":[{"i":{"x":[0.833,0.833,0.833],"y":[0.833,0.833,0.833]},"o":{"x":[0.167,0.167,0.167],"y":[0.167,0.167,0.167]},"n":["0p833_0p833_0p167_0p167","0p833_0p833_0p167_0p167","0p833_0p833_0p167_0p167"],"t":4,"s":[0,0,100],"e":[100,100,100]},{"t":7}],"ix":6}},"ao":0,"shapes":[{"ty":"gr","it":[{"ind":0,"ty":"sh","ix":1,"ks":{"a":0,"k":{"i":[[0,-34.879],[34.879,0],[0,34.879],[-34.88,0]],"o":[[0,34.879],[-34.88,0],[0,-34.879],[34.879,0]],"v":[[63.155,0],[0.001,63.154],[-63.155,0],[0.001,-63.154]],"c":true},"ix":2},"nm":"Trazado 1","mn":"ADBE Vector Shape - Group","hd":false},{"ty":"st","c":{"a":0,"k":[0.128999986836,0.097999999102,0.081999999402,1],"ix":3},"o":{"a":0,"k":100,"ix":4},"w":{"a":0,"k":12,"ix":5},"lc":1,"lj":1,"ml":10,"ml2":{"a":0,"k":10,"ix":8},"nm":"Trazo 1","mn":"ADBE Vector Graphic - Stroke","hd":false},{"ty":"gf","o":{"a":0,"k":100,"ix":10},"r":1,"g":{"p":3,"k":{"a":0,"k":[0,0.984,0.384,0.231,0.5,0.982,0.341,0.265,1,0.98,0.298,0.298],"ix":9}},"s":{"a":0,"k":[0,0],"ix":5},"e":{"a":0,"k":[100,0],"ix":6},"t":1,"nm":"Relleno de degradado 1","mn":"ADBE Vector Graphic - G-Fill","hd":false},{"ty":"tr","p":{"a":0,"k":[538.285,274.919],"ix":2},"a":{"a":0,"k":[0,0],"ix":1},"s":{"a":0,"k":[100,100],"ix":3},"r":{"a":0,"k":0,"ix":6},"o":{"a":0,"k":100,"ix":7},"sk":{"a":0,"k":0,"ix":4},"sa":{"a":0,"k":0,"ix":5},"nm":"Transformar"}],"nm":"Grupo 1","np":3,"cix":2,"ix":1,"mn":"ADBE Vector Group","hd":false}],"ip":0,"op":625,"st":0,"bm":0},{"ddd":0,"ind":2,"ty":4,"nm":"punto 1/mensajeria contornos","sr":1,"ks":{"o":{"a":1,"k":[{"i":{"x":[0.833],"y":[0.833]},"o":{"x":[0.167],"y":[0.167]},"n":["0p833_0p833_0p167_0p167"],"t":20,"s":[100],"e":[0]},{"t":23}],"ix":11},"r":{"a":0,"k":0,"ix":10},"p":{"a":0,"k":[400,400,0],"ix":2},"a":{"a":0,"k":[400,400,0],"ix":1},"s":{"a":0,"k":[100,100,100],"ix":6}},"ao":0,"shapes":[{"ty":"gr","it":[{"ind":0,"ty":"sh","ix":1,"ks":{"a":0,"k":{"i":[[0,9.855],[-9.566,0],[0,-10.134],[10.146,0]],"o":[[0,-10.134],[9.588,0],[0,9.855],[-9.587,0]],"v":[[-16.288,0.005],[0.123,-17.253],[16.288,0.005],[-0.145,17.253]],"c":true},"ix":2},"nm":"Trazado 1","mn":"ADBE Vector Shape - Group","hd":false},{"ty":"fl","c":{"a":0,"k":[0,0,0,1],"ix":4},"o":{"a":0,"k":100,"ix":5},"r":1,"nm":"Relleno 1","mn":"ADBE Vector Graphic - Fill","hd":false},{"ty":"tr","p":{"a":0,"k":[319.831,406.252],"ix":2},"a":{"a":0,"k":[0,0],"ix":1},"s":{"a":0,"k":[100,100],"ix":3},"r":{"a":0,"k":0,"ix":6},"o":{"a":0,"k":100,"ix":7},"sk":{"a":0,"k":0,"ix":4},"sa":{"a":0,"k":0,"ix":5},"nm":"Transformar"}],"nm":"Grupo 1","np":2,"cix":2,"ix":1,"mn":"ADBE Vector Group","hd":false}],"ip":15,"op":24,"st":15,"bm":0},{"ddd":0,"ind":3,"ty":4,"nm":"punto 2/mensajeria contornos","sr":1,"ks":{"o":{"a":1,"k":[{"i":{"x":[0.833],"y":[0.833]},"o":{"x":[0.167],"y":[0.167]},"n":["0p833_0p833_0p167_0p167"],"t":25,"s":[100],"e":[0]},{"t":28}],"ix":11},"r":{"a":0,"k":0,"ix":10},"p":{"a":0,"k":[400,400,0],"ix":2},"a":{"a":0,"k":[400,400,0],"ix":1},"s":{"a":0,"k":[100,100,100],"ix":6}},"ao":0,"shapes":[{"ty":"gr","it":[{"ind":0,"ty":"sh","ix":1,"ks":{"a":0,"k":{"i":[[0,9.855],[-9.588,0],[0,-10.134],[10.145,0]],"o":[[0,-10.134],[9.566,0],[0,9.855],[-9.588,0]],"v":[[-16.288,0.005],[0.145,-17.253],[16.288,0.005],[-0.145,17.253]],"c":true},"ix":2},"nm":"Trazado 1","mn":"ADBE Vector Shape - Group","hd":false},{"ty":"fl","c":{"a":0,"k":[0,0,0,1],"ix":4},"o":{"a":0,"k":100,"ix":5},"r":1,"nm":"Relleno 1","mn":"ADBE Vector Graphic - Fill","hd":false},{"ty":"tr","p":{"a":0,"k":[390.533,406.252],"ix":2},"a":{"a":0,"k":[0,0],"ix":1},"s":{"a":0,"k":[100,100],"ix":3},"r":{"a":0,"k":0,"ix":6},"o":{"a":0,"k":100,"ix":7},"sk":{"a":0,"k":0,"ix":4},"sa":{"a":0,"k":0,"ix":5},"nm":"Transformar"}],"nm":"Grupo 1","np":2,"cix":2,"ix":1,"mn":"ADBE Vector Group","hd":false}],"ip":20,"op":29,"st":20,"bm":0},{"ddd":0,"ind":4,"ty":4,"nm":"punto 3/mensajeria contornos","sr":1,"ks":{"o":{"a":1,"k":[{"i":{"x":[0.833],"y":[0.833]},"o":{"x":[0.167],"y":[0.167]},"n":["0p833_0p833_0p167_0p167"],"t":31,"s":[100],"e":[0]},{"t":33}],"ix":11},"r":{"a":0,"k":0,"ix":10},"p":{"a":0,"k":[400,400,0],"ix":2},"a":{"a":0,"k":[400,400,0],"ix":1},"s":{"a":0,"k":[100,100,100],"ix":6}},"ao":0,"shapes":[{"ty":"gr","it":[{"ind":0,"ty":"sh","ix":1,"ks":{"a":0,"k":{"i":[[0,9.855],[-9.565,0],[0,-10.134],[10.145,0]],"o":[[0,-10.134],[9.588,0],[0,9.855],[-9.587,0]],"v":[[-16.288,0.005],[0.122,-17.253],[16.288,0.005],[-0.145,17.253]],"c":true},"ix":2},"nm":"Trazado 1","mn":"ADBE Vector Shape - Group","hd":false},{"ty":"fl","c":{"a":0,"k":[0,0,0,1],"ix":4},"o":{"a":0,"k":100,"ix":5},"r":1,"nm":"Relleno 1","mn":"ADBE Vector Graphic - Fill","hd":false},{"ty":"tr","p":{"a":0,"k":[465.234,406.252],"ix":2},"a":{"a":0,"k":[0,0],"ix":1},"s":{"a":0,"k":[100,100],"ix":3},"r":{"a":0,"k":0,"ix":6},"o":{"a":0,"k":100,"ix":7},"sk":{"a":0,"k":0,"ix":4},"sa":{"a":0,"k":0,"ix":5},"nm":"Transformar"}],"nm":"Grupo 1","np":2,"cix":2,"ix":1,"mn":"ADBE Vector Group","hd":false}],"ip":25,"op":34,"st":25,"bm":0},{"ddd":0,"ind":5,"ty":4,"nm":"punto 1/mensajeria contornos 2","sr":1,"ks":{"o":{"a":1,"k":[{"i":{"x":[0.833],"y":[0.833]},"o":{"x":[0.167],"y":[0.167]},"n":["0p833_0p833_0p167_0p167"],"t":47,"s":[100],"e":[0]},{"t":49}],"ix":11},"r":{"a":0,"k":0,"ix":10},"p":{"a":0,"k":[400,400,0],"ix":2},"a":{"a":0,"k":[400,400,0],"ix":1},"s":{"a":0,"k":[100,100,100],"ix":6}},"ao":0,"shapes":[{"ty":"gr","it":[{"ind":0,"ty":"sh","ix":1,"ks":{"a":0,"k":{"i":[[0,9.855],[-9.566,0],[0,-10.134],[10.146,0]],"o":[[0,-10.134],[9.588,0],[0,9.855],[-9.587,0]],"v":[[-16.288,0.005],[0.123,-17.253],[16.288,0.005],[-0.145,17.253]],"c":true},"ix":2},"nm":"Trazado 1","mn":"ADBE Vector Shape - Group","hd":false},{"ty":"fl","c":{"a":0,"k":[0,0,0,1],"ix":4},"o":{"a":0,"k":100,"ix":5},"r":1,"nm":"Relleno 1","mn":"ADBE Vector Graphic - Fill","hd":false},{"ty":"tr","p":{"a":0,"k":[319.831,406.252],"ix":2},"a":{"a":0,"k":[0,0],"ix":1},"s":{"a":0,"k":[100,100],"ix":3},"r":{"a":0,"k":0,"ix":6},"o":{"a":0,"k":100,"ix":7},"sk":{"a":0,"k":0,"ix":4},"sa":{"a":0,"k":0,"ix":5},"nm":"Transformar"}],"nm":"Grupo 1","np":2,"cix":2,"ix":1,"mn":"ADBE Vector Group","hd":false}],"ip":41,"op":50,"st":41,"bm":0},{"ddd":0,"ind":6,"ty":4,"nm":"punto 2/mensajeria contornos 2","sr":1,"ks":{"o":{"a":1,"k":[{"i":{"x":[0.833],"y":[0.833]},"o":{"x":[0.167],"y":[0.167]},"n":["0p833_0p833_0p167_0p167"],"t":56,"s":[100],"e":[0]},{"t":59}],"ix":11},"r":{"a":0,"k":0,"ix":10},"p":{"a":0,"k":[400,400,0],"ix":2},"a":{"a":0,"k":[400,400,0],"ix":1},"s":{"a":0,"k":[100,100,100],"ix":6}},"ao":0,"shapes":[{"ty":"gr","it":[{"ind":0,"ty":"sh","ix":1,"ks":{"a":0,"k":{"i":[[0,9.855],[-9.588,0],[0,-10.134],[10.145,0]],"o":[[0,-10.134],[9.566,0],[0,9.855],[-9.588,0]],"v":[[-16.288,0.005],[0.145,-17.253],[16.288,0.005],[-0.145,17.253]],"c":true},"ix":2},"nm":"Trazado 1","mn":"ADBE Vector Shape - Group","hd":false},{"ty":"fl","c":{"a":0,"k":[0,0,0,1],"ix":4},"o":{"a":0,"k":100,"ix":5},"r":1,"nm":"Relleno 1","mn":"ADBE Vector Graphic - Fill","hd":false},{"ty":"tr","p":{"a":0,"k":[390.533,406.252],"ix":2},"a":{"a":0,"k":[0,0],"ix":1},"s":{"a":0,"k":[100,100],"ix":3},"r":{"a":0,"k":0,"ix":6},"o":{"a":0,"k":100,"ix":7},"sk":{"a":0,"k":0,"ix":4},"sa":{"a":0,"k":0,"ix":5},"nm":"Transformar"}],"nm":"Grupo 1","np":2,"cix":2,"ix":1,"mn":"ADBE Vector Group","hd":false}],"ip":46,"op":55,"st":46,"bm":0},{"ddd":0,"ind":7,"ty":4,"nm":"punto 3/mensajeria contornos 2","sr":1,"ks":{"o":{"a":1,"k":[{"i":{"x":[0.833],"y":[0.833]},"o":{"x":[0.167],"y":[0.167]},"n":["0p833_0p833_0p167_0p167"],"t":56,"s":[100],"e":[0]},{"t":58}],"ix":11},"r":{"a":0,"k":0,"ix":10},"p":{"a":0,"k":[400,400,0],"ix":2},"a":{"a":0,"k":[400,400,0],"ix":1},"s":{"a":0,"k":[100,100,100],"ix":6}},"ao":0,"shapes":[{"ty":"gr","it":[{"ind":0,"ty":"sh","ix":1,"ks":{"a":0,"k":{"i":[[0,9.855],[-9.565,0],[0,-10.134],[10.145,0]],"o":[[0,-10.134],[9.588,0],[0,9.855],[-9.587,0]],"v":[[-16.288,0.005],[0.122,-17.253],[16.288,0.005],[-0.145,17.253]],"c":true},"ix":2},"nm":"Trazado 1","mn":"ADBE Vector Shape - Group","hd":false},{"ty":"fl","c":{"a":0,"k":[0,0,0,1],"ix":4},"o":{"a":0,"k":100,"ix":5},"r":1,"nm":"Relleno 1","mn":"ADBE Vector Graphic - Fill","hd":false},{"ty":"tr","p":{"a":0,"k":[465.234,406.252],"ix":2},"a":{"a":0,"k":[0,0],"ix":1},"s":{"a":0,"k":[100,100],"ix":3},"r":{"a":0,"k":0,"ix":6},"o":{"a":0,"k":100,"ix":7},"sk":{"a":0,"k":0,"ix":4},"sa":{"a":0,"k":0,"ix":5},"nm":"Transformar"}],"nm":"Grupo 1","np":2,"cix":2,"ix":1,"mn":"ADBE Vector Group","hd":false}],"ip":51,"op":60,"st":51,"bm":0},{"ddd":0,"ind":8,"ty":1,"nm":"Sólido Blanco 1","td":1,"sr":1,"ks":{"o":{"a":0,"k":100,"ix":11},"r":{"a":0,"k":0,"ix":10},"p":{"a":0,"k":[392,424,0],"ix":2},"a":{"a":0,"k":[255.5,282.5,0],"ix":1},"s":{"a":0,"k":[81.213,63.894,100],"ix":6}},"ao":0,"sw":511,"sh":565,"sc":"#ffffff","ip":0,"op":625,"st":0,"bm":0},{"ddd":0,"ind":9,"ty":4,"nm":"mensaje/mensajeria contornos","tt":1,"sr":1,"ks":{"o":{"a":0,"k":100,"ix":11},"r":{"a":0,"k":0,"ix":10},"p":{"a":0,"k":[400,400,0],"ix":2},"a":{"a":0,"k":[400,400,0],"ix":1},"s":{"a":0,"k":[100,100,100],"ix":6}},"ao":0,"shapes":[{"ty":"gr","it":[{"ind":0,"ty":"sh","ix":1,"ks":{"a":0,"k":{"i":[[0,0],[0,0],[0,-31.097],[0,0],[-31.098,0],[0,0],[0,0],[-7.745,7.745],[0,0],[0,0],[0,31.097],[0,0],[31.097,0]],"o":[[0,0],[-31.098,0],[0,0],[0,31.097],[0,0],[0,0],[0,10.952],[0,0],[0,0],[31.097,0],[0,0],[0,-31.097],[0,0]],"v":[[44.342,-166.863],[-126.308,-166.863],[-182.615,-110.557],[-182.615,44.666],[-126.308,100.971],[-103.482,100.971],[-103.482,150.427],[-82.495,159.118],[-24.348,100.971],[126.309,100.971],[182.615,44.666],[182.615,-110.557],[126.309,-166.863]],"c":false},"ix":2},"nm":"Trazado 1","mn":"ADBE Vector Shape - Group","hd":false},{"ty":"st","c":{"a":0,"k":[0,0,0,1],"ix":3},"o":{"a":0,"k":100,"ix":4},"w":{"a":0,"k":12,"ix":5},"lc":2,"lj":2,"nm":"Trazo 1","mn":"ADBE Vector Graphic - Stroke","hd":false},{"ty":"fl","c":{"a":0,"k":[1,1,1,1],"ix":4},"o":{"a":0,"k":100,"ix":5},"r":1,"nm":"Relleno 1","mn":"ADBE Vector Graphic - Fill","hd":false},{"ty":"tr","p":{"a":0,"k":[382.302,427.325],"ix":2},"a":{"a":0,"k":[0,0],"ix":1},"s":{"a":0,"k":[100,100],"ix":3},"r":{"a":0,"k":0,"ix":6},"o":{"a":0,"k":100,"ix":7},"sk":{"a":0,"k":0,"ix":4},"sa":{"a":0,"k":0,"ix":5},"nm":"Transformar"}],"nm":"Grupo 1","np":3,"cix":2,"ix":1,"mn":"ADBE Vector Group","hd":false}],"ip":0,"op":625,"st":0,"bm":0}],"markers":[]}